{
  "id": "0612c6c1-643e-49d4-858c-8304d3cdc52c",
  "data": [
    {
      "entity": "IDENTIF_VEHICULOS_NRSERIE_PLACAS",
      "text": "1234 BCD"
    },
    {
      "entity": "NUMERO_BENEF_PLAN_SALUD",
      "text": "B-45872316"
    },
    {
      "entity": "NUMERO_BENEF_PLAN_SALUD",
      "text": "B-458712369"
    },
    {
      "entity": "OTROS_SUJETO_ASISTENCIA",
      "text": "hermana del paciente"
    },
    {
      "entity": "OTROS_SUJETO_ASISTENCIA",
      "text": "fumador ocasional"
    },
    {
      "entity": "ID_TITULACION_PERSONAL_SANITARIO",
      "text": "Grado en Medicina"
    },
    {
      "entity": "NUMERO_TELEFONO",
      "text": "612-34-56-78"
    },
    {
      "entity": "CORREO_ELECTRONICO",
      "text": "ana.garcia@clinic.es"
    },
    {
      "entity": "URL_WEB",
      "text": "https://www.clinicabarcelona.org"
    },
    {
      "entity": "INSTITUCION",
      "text": "Ministerio de Sanidad"
    },
    {
      "entity": "SEXO_SUJETO_ASISTENCIA",
      "text": "femenino"
    }
  ]
}