{
  "id": "07f563e0-218c-4725-9a66-cbe2da9bd358",
  "data": [
    {
      "entity": "OTRO_NUMERO_IDENTIF",
      "text": "REF-48263915B"
    },
    {
      "entity": "NUMERO_FAX",
      "text": "+34 91 876 54 32"
    },
    {
      "entity": "NOMBRE_PERSONAL_SANITARIO",
      "text": "Dra. Elena Rodríguez"
    },
    {
      "entity": "NOMBRE_PERSONAL_SANITARIO",
      "text": "Dra. Elena Martínez Rodríguez"
    },
    {
      "entity": "SEXO_SUJETO_ASISTENCIA",
      "text": "femenino"
    }
  ]
}