{
  "id": "0aca97fe-0539-4e5d-b84e-a6ceb1d92cd4",
  "data": [
    {
      "entity": "PAIS",
      "text": "España"
    },
    {
      "entity": "SEXO_SUJETO_ASISTENCIA",
      "text": "femenino"
    },
    {
      "entity": "OTRO_NUMERO_IDENTIF",
      "text": "REF-2024-789123"
    },
    {
      "entity": "HOSPITAL",
      "text": "Hospital Clínico San Carlos"
    },
    {
      "entity": "URL_WEB",
      "text": "https://www.clinicabarcelona.org"
    },
    {
      "entity": "ID_ASEGURAMIENTO",
      "text": "B123456789"
    },
    {
      "entity": "CALLE",
      "text": "Avenida del Mediterráneo 12"
    },
    {
      "entity": "CALLE",
      "text": "Avenida de la Constitución 12"
    },
    {
      "entity": "ID_EMPLEO_PERSONAL_SANITARIO",
      "text": "E-78945"
    },
    {
      "entity": "ID_EMPLEO_PERSONAL_SANITARIO",
      "text": "E-459-23"
    },
    {
      "entity": "FECHAS",
      "text": "12 de julio de 2023"
    },
    {
      "entity": "EDAD_SUJETO_ASISTENCIA",
      "text": "67 años"
    },
    {
      "entity": "TERRITORIO",
      "text": "Comunidad Valenciana"
    }
  ]
}