{
  "id": "19105ce8-6b85-40b6-aec9-14d82c12a7de",
  "data": [
    {
      "entity": "PROFESION",
      "text": "cirujano"
    },
    {
      "entity": "TERRITORIO",
      "text": "Comunidad Valenciana"
    },
    {
      "entity": "URL_WEB",
      "text": "https://www.clinicabarcelona.org"
    },
    {
      "entity": "ID_TITULACION_PERSONAL_SANITARIO",
      "text": "Grado en Medicina"
    },
    {
      "entity": "CALLE",
      "text": "Avenida de la Constitución 12"
    },
    {
      "entity": "NUMERO_BENEF_PLAN_SALUD",
      "text": "B-45872316"
    }
  ]
}