{
  "id": "1fbc5198-2f4d-4348-b52a-56171d1609ed",
  "data": [
    {
      "entity": "URL_WEB",
      "text": "https://www.clinicabarcelona.org/cita-previa"
    },
    {
      "entity": "TERRITORIO",
      "text": "Comunidad Valenciana"
    },
    {
      "entity": "CALLE",
      "text": "Avenida de la Constitución 12"
    },
    {
      "entity": "NOMBRE_SUJETO_ASISTENCIA",
      "text": "Laura Méndez Iglesias"
    },
    {
      "entity": "NUMERO_BENEF_PLAN_SALUD",
      "text": "B-45872316"
    },
    {
      "entity": "NUMERO_TELEFONO",
      "text": "612-34-56-78"
    },
    {
      "entity": "ID_SUJETO_ASISTENCIA",
      "text": "87654321B"
    },
    {
      "entity": "EDAD_SUJETO_ASISTENCIA",
      "text": "67 años"
    },
    {
      "entity": "CORREO_ELECTRONICO",
      "text": "carlos.martinez@clinic.es"
    },
    {
      "entity": "CENTRO_SALUD",
      "text": "Centro de Salud Los Álamos"
    },
    {
      "entity": "OTROS_SUJETO_ASISTENCIA",
      "text": "alérgico a la penicilina"
    }
  ]
}