{
  "id": "219b5d59-854d-48d9-957c-4231b537552f",
  "data": [
    {
      "entity": "NOMBRE_SUJETO_ASISTENCIA",
      "text": "Laura Méndez Iglesias"
    },
    {
      "entity": "INSTITUCION",
      "text": "Ministerio de Sanidad"
    },
    {
      "entity": "NOMBRE_PERSONAL_SANITARIO",
      "text": "Dra. Elena Rodríguez Santos"
    },
    {
      "entity": "OTROS_SUJETO_ASISTENCIA",
      "text": "Grupo de apoyo para pacientes con diabetes"
    },
    {
      "entity": "ID_CONTACTO_ASISTENCIAL",
      "text": "HC-2024-789012"
    },
    {
      "entity": "DIREC_PROT_INTERNET",
      "text": "https://historiaclinica.hgugm.es/paciente/12345"
    },
    {
      "entity": "HOSPITAL",
      "text": "Hospital Clínico San Carlos"
    },
    {
      "entity": "OTRO_NUMERO_IDENTIF",
      "text": "HC-2024-789012"
    },
    {
      "entity": "PAIS",
      "text": "España"
    },
    {
      "entity": "URL_WEB",
      "text": "https://www.clinicabarcelona.org"
    }
  ]
}