{
  "id": "2f4c831d-55fc-48d7-b433-86296c3544d8",
  "data": [
    {
      "entity": "IDENTIF_BIOMETRICOS",
      "text": "huella dactilar derecha índice, patrón de arco"
    },
    {
      "entity": "CENTRO_SALUD",
      "text": "Centro de Salud Los Álamos"
    },
    {
      "entity": "FECHAS",
      "text": "12 de julio de 2023"
    },
    {
      "entity": "ID_TITULACION_PERSONAL_SANITARIO",
      "text": "Grado en Medicina"
    },
    {
      "entity": "OTRO_NUMERO_IDENTIF",
      "text": "HC-2024-789456"
    },
    {
      "entity": "OTRO_NUMERO_IDENTIF",
      "text": "REF-87463215B"
    },
    {
      "entity": "NUMERO_TELEFONO",
      "text": "+34 912 34 56 78"
    },
    {
      "entity": "OTROS_SUJETO_ASISTENCIA",
      "text": "Grupo de apoyo de diabetes tipo 2"
    }
  ]
}