{
  "id": "327d3040-b589-4b9f-9936-46d726ebd4f4",
  "data": [
    {
      "entity": "ID_CONTACTO_ASISTENCIAL",
      "text": "HC-2024-789012"
    },
    {
      "entity": "ID_CONTACTO_ASISTENCIAL",
      "text": "HC-2024-789123"
    },
    {
      "entity": "TERRITORIO",
      "text": "Comunidad Valenciana"
    },
    {
      "entity": "ID_SUJETO_ASISTENCIA",
      "text": "87654321B"
    },
    {
      "entity": "IDENTIF_DISPOSITIVOS_NRSERIE",
      "text": "SN-98246731"
    },
    {
      "entity": "INSTITUCION",
      "text": "Servicio Andaluz de Salud"
    },
    {
      "entity": "INSTITUCION",
      "text": "Ministerio de Sanidad"
    },
    {
      "entity": "NUMERO_FAX",
      "text": "+34 91 876 54 32"
    },
    {
      "entity": "CENTRO_SALUD",
      "text": "Centro de Salud Los Álamos"
    },
    {
      "entity": "ID_TITULACION_PERSONAL_SANITARIO",
      "text": "Grado en Enfermería"
    },
    {
      "entity": "ID_TITULACION_PERSONAL_SANITARIO",
      "text": "Grado en Medicina"
    },
    {
      "entity": "PAIS",
      "text": "España"
    },
    {
      "entity": "OTRO_NUMERO_IDENTIF",
      "text": "REF-48263915B"
    },
    {
      "entity": "PROFESION",
      "text": "médico"
    },
    {
      "entity": "PROFESION",
      "text": "médico residente"
    },
    {
      "entity": "PROFESION",
      "text": "cirujano"
    },
    {
      "entity": "IDENTIF_VEHICULOS_NRSERIE_PLACAS",
      "text": "1234 BCD"
    }
  ]
}