{
  "id": "34886cab-860b-4a23-b7fe-a6f656147776",
  "data": [
    {
      "entity": "HOSPITAL",
      "text": "Hospital Clínico San Carlos"
    },
    {
      "entity": "ID_TITULACION_PERSONAL_SANITARIO",
      "text": "Grado en Medicina"
    },
    {
      "entity": "NUMERO_FAX",
      "text": "+34 91 876 54 32"
    },
    {
      "entity": "IDENTIF_DISPOSITIVOS_NRSERIE",
      "text": "SN-98237641"
    },
    {
      "entity": "SEXO_SUJETO_ASISTENCIA",
      "text": "femenino"
    },
    {
      "entity": "INSTITUCION",
      "text": "Ministerio de Sanidad"
    }
  ]
}