{
  "id": "3aff0586-578b-4ef1-985c-ceba3c4d7ba9",
  "data": [
    {
      "entity": "INSTITUCION",
      "text": "Consejería de Salud de la Comunidad de Madrid"
    },
    {
      "entity": "INSTITUCION",
      "text": "Ministerio de Sanidad"
    },
    {
      "entity": "HOSPITAL",
      "text": "Hospital Clínico San Carlos"
    },
    {
      "entity": "FECHAS",
      "text": "12 de julio de 2023"
    },
    {
      "entity": "EDAD_SUJETO_ASISTENCIA",
      "text": "67 años"
    },
    {
      "entity": "NUMERO_TELEFONO",
      "text": "612-34-56-78"
    },
    {
      "entity": "SEXO_SUJETO_ASISTENCIA",
      "text": "femenino"
    },
    {
      "entity": "NOMBRE_SUJETO_ASISTENCIA",
      "text": "Laura Méndez Iglesias"
    },
    {
      "entity": "IDENTIF_DISPOSITIVOS_NRSERIE",
      "text": "SN-84736251"
    },
    {
      "entity": "DIREC_PROT_INTERNET",
      "text": "https://historiaclinica.hgugm.es/paciente/12345678A"
    },
    {
      "entity": "TERRITORIO",
      "text": "Comunidad Valenciana"
    }
  ]
}