{
  "id": "40d2d137-c64b-4906-a17f-20e494d96ec8",
  "data": [
    {
      "entity": "TERRITORIO",
      "text": "Comunidad Valenciana"
    },
    {
      "entity": "CENTRO_SALUD",
      "text": "Centro de Salud Los Álamos"
    },
    {
      "entity": "IDENTIF_VEHICULOS_NRSERIE_PLACAS",
      "text": "1234 BCD"
    },
    {
      "entity": "URL_WEB",
      "text": "www.saludcantabria.es"
    },
    {
      "entity": "PROFESION",
      "text": "cirujano cardiovascular"
    },
    {
      "entity": "DIREC_PROT_INTERNET",
      "text": "https://historiaclinica.hgugm.es/paciente/12345678A"
    },
    {
      "entity": "DIREC_PROT_INTERNET",
      "text": "https://api.hospitalcentral.es/pacientes/12345678A"
    },
    {
      "entity": "OTROS_SUJETO_ASISTENCIA",
      "text": "Grupo de apoyo de diabetes tipo 2"
    },
    {
      "entity": "ID_EMPLEO_PERSONAL_SANITARIO",
      "text": "E-987654"
    },
    {
      "entity": "IDENTIF_DISPOSITIVOS_NRSERIE",
      "text": "SN-98237641"
    },
    {
      "entity": "SEXO_SUJETO_ASISTENCIA",
      "text": "femenino"
    },
    {
      "entity": "CORREO_ELECTRONICO",
      "text": "carlos.martinez@clinic.es"
    }
  ]
}