{
  "id": "459276e6-2b1d-4ad5-9723-725b0d62808d",
  "data": [
    {
      "entity": "SEXO_SUJETO_ASISTENCIA",
      "text": "femenino"
    },
    {
      "entity": "ID_SUJETO_ASISTENCIA",
      "text": "B-78423915"
    },
    {
      "entity": "ID_SUJETO_ASISTENCIA",
      "text": "87654321B"
    },
    {
      "entity": "OTROS_SUJETO_ASISTENCIA",
      "text": "Grupo de apoyo para la ansiedad"
    },
    {
      "entity": "OTROS_SUJETO_ASISTENCIA",
      "text": "alergia a la penicilina"
    },
    {
      "entity": "ID_EMPLEO_PERSONAL_SANITARIO",
      "text": "E-789456"
    },
    {
      "entity": "ID_EMPLEO_PERSONAL_SANITARIO",
      "text": "E-459-23"
    },
    {
      "entity": "NUMERO_TELEFONO",
      "text": "612-34-56-78"
    },
    {
      "entity": "FAMILIARES_SUJETO_ASISTENCIA",
      "text": "María del Carmen Rodríguez"
    },
    {
      "entity": "PROFESION",
      "text": "cirujano"
    },
    {
      "entity": "OTRO_NUMERO_IDENTIF",
      "text": "REF-7348291B"
    },
    {
      "entity": "OTRO_NUMERO_IDENTIF",
      "text": "HC-2024-789012"
    }
  ]
}