{
  "id": "4804f005-cade-46c7-9198-f07f06f72591",
  "data": [
    {
      "entity": "ID_SUJETO_ASISTENCIA",
      "text": "12345678A"
    },
    {
      "entity": "OTROS_SUJETO_ASISTENCIA",
      "text": "otro sujeto de asistencia"
    },
    {
      "entity": "OTROS_SUJETO_ASISTENCIA",
      "text": "familiar"
    },
    {
      "entity": "IDENTIF_BIOMETRICOS",
      "text": "12345678A"
    },
    {
      "entity": "IDENTIF_VEHICULOS_NRSERIE_PLACAS",
      "text": "1234 ABC"
    },
    {
      "entity": "URL_WEB",
      "text": "https://meddocan.herokuapp.com/"
    },
    {
      "entity": "ID_ASEGURAMIENTO",
      "text": "A123456789"
    },
    {
      "entity": "NOMBRE_SUJETO_ASISTENCIA",
      "text": "Juan Pérez García"
    },
    {
      "entity": "NOMBRE_SUJETO_ASISTENCIA",
      "text": "María López Martínez"
    },
    {
      "entity": "FAMILIARES_SUJETO_ASISTENCIA",
      "text": "hermano"
    },
    {
      "entity": "PROFESION",
      "text": "enfermero"
    },
    {
      "entity": "CORREO_ELECTRONICO",
      "text": "juan.perez@ejemplo.com"
    }
  ]
}