{
  "id": "4934d173-e85c-41c2-8126-4b9fd001e8f1",
  "data": [
    {
      "entity": "CALLE",
      "text": "Avenida de la Albufera 127"
    },
    {
      "entity": "OTROS_SUJETO_ASISTENCIA",
      "text": "alergia a la penicilina"
    },
    {
      "entity": "OTROS_SUJETO_ASISTENCIA",
      "text": "fumador ocasional"
    },
    {
      "entity": "NUMERO_BENEF_PLAN_SALUD",
      "text": "B-58479216"
    },
    {
      "entity": "NUMERO_BENEF_PLAN_SALUD",
      "text": "B-458712369"
    }
  ]
}