{
  "id": "4ddced6a-2194-4117-8b40-10f918e5bfad",
  "data": [
    {
      "entity": "NUMERO_TELEFONO",
      "text": "612-34-56-78"
    },
    {
      "entity": "NOMBRE_PERSONAL_SANITARIO",
      "text": "Dra. Elena Rodríguez Santos"
    },
    {
      "entity": "ID_EMPLEO_PERSONAL_SANITARIO",
      "text": "E-459-23"
    },
    {
      "entity": "ID_EMPLEO_PERSONAL_SANITARIO",
      "text": "E-789456"
    },
    {
      "entity": "NUMERO_BENEF_PLAN_SALUD",
      "text": "B-45872316"
    },
    {
      "entity": "NUMERO_BENEF_PLAN_SALUD",
      "text": "B123456789"
    },
    {
      "entity": "NUMERO_FAX",
      "text": "+34 91 876 54 32"
    }
  ]
}