{
  "id": "53f07854-5f10-417c-a7c5-feee2507d8e7",
  "data": [
    {
      "entity": "ID_ASEGURAMIENTO",
      "text": "B123456789"
    },
    {
      "entity": "ID_SUJETO_ASISTENCIA",
      "text": "87654321B"
    },
    {
      "entity": "OTRO_NUMERO_IDENTIF",
      "text": "REF-2024-789456"
    },
    {
      "entity": "NOMBRE_PERSONAL_SANITARIO",
      "text": "Dra. Elena Rodríguez"
    },
    {
      "entity": "NOMBRE_PERSONAL_SANITARIO",
      "text": "Dra. Elena Rodríguez Santos"
    },
    {
      "entity": "FAMILIARES_SUJETO_ASISTENCIA",
      "text": "María José Fernández López"
    },
    {
      "entity": "FECHAS",
      "text": "12 de julio de 2023"
    },
    {
      "entity": "CALLE",
      "text": "Avenida del Mediterráneo 12"
    },
    {
      "entity": "URL_WEB",
      "text": "https://www.clinicabarcelona.org"
    },
    {
      "entity": "INSTITUCION",
      "text": "Ministerio de Sanidad"
    },
    {
      "entity": "INSTITUCION",
      "text": "Consejería de Salud de la Comunidad de Madrid"
    }
  ]
}