{
  "id": "565cce83-c1aa-4c94-b31a-324bf5ce79d3",
  "data": [
    {
      "entity": "OTRO_NUMERO_IDENTIF",
      "text": "B-58329147"
    },
    {
      "entity": "FAMILIARES_SUJETO_ASISTENCIA",
      "text": "María González López"
    },
    {
      "entity": "PAIS",
      "text": "España"
    },
    {
      "entity": "IDENTIF_DISPOSITIVOS_NRSERIE",
      "text": "SN-98237641"
    },
    {
      "entity": "NUMERO_FAX",
      "text": "+34 91 876 54 32"
    },
    {
      "entity": "IDENTIF_BIOMETRICOS",
      "text": "huella dactilar derecha índice"
    },
    {
      "entity": "IDENTIF_BIOMETRICOS",
      "text": "Huella dactilar derecha, índice"
    }
  ]
}