{
  "id": "59591076-4e47-43d1-9290-ccd3a3d5d177",
  "data": [
    {
      "entity": "DIREC_PROT_INTERNET",
      "text": "https://www.hospitalregional.es/pacientes/consulta-resultados"
    },
    {
      "entity": "NUMERO_TELEFONO",
      "text": "612-34-56-78"
    },
    {
      "entity": "URL_WEB",
      "text": "https://www.clinicabarcelona.org"
    },
    {
      "entity": "CENTRO_SALUD",
      "text": "Centro de Salud Los Álamos"
    },
    {
      "entity": "CORREO_ELECTRONICO",
      "text": "ana.garcia@clinic.es"
    }
  ]
}