{
  "id": "5db0d4a6-c7ec-4575-a570-7f5dab20b23e",
  "data": [
    {
      "entity": "ID_EMPLEO_PERSONAL_SANITARIO",
      "text": "E-789456"
    },
    {
      "entity": "NUMERO_FAX",
      "text": "+34 91 876 54 32"
    },
    {
      "entity": "OTRO_NUMERO_IDENTIF",
      "text": "REF-48263915B"
    },
    {
      "entity": "IDENTIF_DISPOSITIVOS_NRSERIE",
      "text": "SN-98237641"
    },
    {
      "entity": "IDENTIF_DISPOSITIVOS_NRSERIE",
      "text": "SN-98246731"
    },
    {
      "entity": "ID_ASEGURAMIENTO",
      "text": "B123456789"
    },
    {
      "entity": "ID_SUJETO_ASISTENCIA",
      "text": "87654321B"
    }
  ]
}