{
  "id": "68d2cc61-f92f-4ff9-951f-b6107671c8a1",
  "data": [
    {
      "entity": "ID_ASEGURAMIENTO",
      "text": "ES-87654321-1"
    },
    {
      "entity": "NUMERO_TELEFONO",
      "text": "612-34-56-78"
    },
    {
      "entity": "NUMERO_TELEFONO",
      "text": "612-345-678"
    },
    {
      "entity": "NOMBRE_SUJETO_ASISTENCIA",
      "text": "Ana Rodríguez López"
    },
    {
      "entity": "URL_WEB",
      "text": "https://www.clinicabarcelona.org"
    },
    {
      "entity": "CORREO_ELECTRONICO",
      "text": "carlos.martinez@clinic.es"
    },
    {
      "entity": "OTROS_SUJETO_ASISTENCIA",
      "text": "Grupo de apoyo oncológico"
    },
    {
      "entity": "IDENTIF_VEHICULOS_NRSERIE_PLACAS",
      "text": "1234 BCD"
    },
    {
      "entity": "FECHAS",
      "text": "12 de julio de 2023"
    }
  ]
}