{
  "id": "6e215da8-77a7-4708-b4ad-706820314ec2",
  "data": [
    {
      "entity": "NUMERO_BENEF_PLAN_SALUD",
      "text": "B-458712369"
    },
    {
      "entity": "NUMERO_BENEF_PLAN_SALUD",
      "text": "B123456789"
    },
    {
      "entity": "NUMERO_FAX",
      "text": "+34 91 876 54 32"
    },
    {
      "entity": "OTROS_SUJETO_ASISTENCIA",
      "text": "alérgico a la penicilina"
    },
    {
      "entity": "FECHAS",
      "text": "12 de julio de 2023"
    },
    {
      "entity": "SEXO_SUJETO_ASISTENCIA",
      "text": "femenino"
    },
    {
      "entity": "EDAD_SUJETO_ASISTENCIA",
      "text": "67 años"
    },
    {
      "entity": "CALLE",
      "text": "Avenida de la Constitución 12"
    },
    {
      "entity": "CALLE",
      "text": "Avenida de la Albufera 127"
    },
    {
      "entity": "ID_CONTACTO_ASISTENCIAL",
      "text": "HC-2024-789012"
    }
  ]
}