{
  "id": "76ebb5aa-e0b8-47e2-addc-0f825c1571b6",
  "data": [
    {
      "entity": "ID_SUJETO_ASISTENCIA",
      "text": "87654321B"
    },
    {
      "entity": "NUMERO_TELEFONO",
      "text": "612-34-56-78"
    },
    {
      "entity": "PAIS",
      "text": "España"
    },
    {
      "entity": "CORREO_ELECTRONICO",
      "text": "carlos.martinez@clinic.es"
    },
    {
      "entity": "CENTRO_SALUD",
      "text": "Centro de Salud Los Álamos"
    },
    {
      "entity": "PROFESION",
      "text": "cirujano"
    }
  ]
}