{
  "id": "8d1ee612-a030-4463-82c8-cacf10b44241",
  "data": [
    {
      "entity": "CORREO_ELECTRONICO",
      "text": "carlos.martinez@clinic.es"
    },
    {
      "entity": "ID_TITULACION_PERSONAL_SANITARIO",
      "text": "Grado en Medicina"
    },
    {
      "entity": "PAIS",
      "text": "España"
    },
    {
      "entity": "ID_CONTACTO_ASISTENCIAL",
      "text": "HC-2024-B-8472"
    },
    {
      "entity": "NOMBRE_SUJETO_ASISTENCIA",
      "text": "Laura Méndez Iglesias"
    },
    {
      "entity": "NOMBRE_SUJETO_ASISTENCIA",
      "text": "Laura Díaz Méndez"
    },
    {
      "entity": "IDENTIF_BIOMETRICOS",
      "text": "huella dactilar del dedo índice derecho"
    },
    {
      "entity": "FECHAS",
      "text": "12 de julio de 2023"
    }
  ]
}