{
  "id": "8ffd801b-eec7-4384-a922-183a3f0ca134",
  "data": [
    {
      "entity": "CENTRO_SALUD",
      "text": "Centro de Salud Los Álamos"
    },
    {
      "entity": "HOSPITAL",
      "text": "Hospital Clínico San Carlos"
    },
    {
      "entity": "NUMERO_TELEFONO",
      "text": "612-345-678"
    },
    {
      "entity": "EDAD_SUJETO_ASISTENCIA",
      "text": "78 años"
    },
    {
      "entity": "IDENTIF_VEHICULOS_NRSERIE_PLACAS",
      "text": "1234 BCD"
    },
    {
      "entity": "ID_CONTACTO_ASISTENCIAL",
      "text": "HC-2024-789012"
    },
    {
      "entity": "DIREC_PROT_INTERNET",
      "text": "https://historiaclinica.hgugm.es/paciente/12345"
    },
    {
      "entity": "DIREC_PROT_INTERNET",
      "text": "https://historiaclinica.hgugm.es/paciente/12345678A"
    },
    {
      "entity": "ID_ASEGURAMIENTO",
      "text": "ES-87654321-A"
    },
    {
      "entity": "ID_ASEGURAMIENTO",
      "text": "ES-4567890123"
    },
    {
      "entity": "ID_ASEGURAMIENTO",
      "text": "B27456890"
    },
    {
      "entity": "SEXO_SUJETO_ASISTENCIA",
      "text": "femenino"
    },
    {
      "entity": "NOMBRE_PERSONAL_SANITARIO",
      "text": "Dra. Elena Rodríguez Santos"
    },
    {
      "entity": "PAIS",
      "text": "España"
    }
  ]
}