{
  "id": "9b13b965-ad42-40fc-97b8-9d7d03799450",
  "data": [
    {
      "entity": "OTROS_SUJETO_ASISTENCIA",
      "text": "hermano del paciente"
    },
    {
      "entity": "TERRITORIO",
      "text": "Comunidad Valenciana"
    },
    {
      "entity": "ID_TITULACION_PERSONAL_SANITARIO",
      "text": "Grado en Medicina"
    },
    {
      "entity": "DIREC_PROT_INTERNET",
      "text": "https://historiaclinica.hospitalcentral.es/paciente/area_privada"
    },
    {
      "entity": "SEXO_SUJETO_ASISTENCIA",
      "text": "femenino"
    },
    {
      "entity": "ID_CONTACTO_ASISTENCIAL",
      "text": "HC-2024-789012"
    },
    {
      "entity": "ID_CONTACTO_ASISTENCIAL",
      "text": "CON-2024-8741"
    },
    {
      "entity": "FECHAS",
      "text": "12 de julio de 2023"
    },
    {
      "entity": "HOSPITAL",
      "text": "Hospital Clínico San Carlos"
    },
    {
      "entity": "NUMERO_TELEFONO",
      "text": "612-34-56-78"
    }
  ]
}