{
  "id": "9b3eaea2-3b0f-4506-a447-3efed221301b",
  "data": [
    {
      "entity": "OTROS_SUJETO_ASISTENCIA",
      "text": "fumador ocasional"
    },
    {
      "entity": "SEXO_SUJETO_ASISTENCIA",
      "text": "femenino"
    },
    {
      "entity": "PAIS",
      "text": "España"
    },
    {
      "entity": "IDENTIF_BIOMETRICOS",
      "text": "Huella dactilar derecha índice, patrón de lazo"
    },
    {
      "entity": "IDENTIF_BIOMETRICOS",
      "text": "huella dactilar del pulgar derecho"
    }
  ]
}