{
  "id": "9e634a50-b0a6-407f-a10a-c4c8a9143345",
  "data": [
    {
      "entity": "TERRITORIO",
      "text": "Comunidad Valenciana"
    },
    {
      "entity": "FECHAS",
      "text": "12 de noviembre de 2023"
    },
    {
      "entity": "CALLE",
      "text": "Avenida del Mediterráneo 12"
    },
    {
      "entity": "ID_CONTACTO_ASISTENCIAL",
      "text": "HC-2024-789012"
    },
    {
      "entity": "FAMILIARES_SUJETO_ASISTENCIA",
      "text": "María del Carmen Gutiérrez, madre"
    },
    {
      "entity": "ID_EMPLEO_PERSONAL_SANITARIO",
      "text": "E-2023-8741"
    },
    {
      "entity": "URL_WEB",
      "text": "https://www.clinicabarcelona.org"
    },
    {
      "entity": "NOMBRE_SUJETO_ASISTENCIA",
      "text": "Laura Díaz Méndez"
    },
    {
      "entity": "NOMBRE_SUJETO_ASISTENCIA",
      "text": "Laura Méndez Iglesias"
    },
    {
      "entity": "CENTRO_SALUD",
      "text": "Centro de Salud Los Álamos"
    },
    {
      "entity": "DIREC_PROT_INTERNET",
      "text": "https://historiaclinica.hospitalcentral.es/paciente/ZXC456"
    },
    {
      "entity": "INSTITUCION",
      "text": "Consejería de Salud de la Comunidad de Madrid"
    },
    {
      "entity": "OTROS_SUJETO_ASISTENCIA",
      "text": "Grupo de apoyo de pacientes con diabetes"
    },
    {
      "entity": "OTROS_SUJETO_ASISTENCIA",
      "text": "grupo de apoyo para la ansiedad"
    }
  ]
}