{
  "id": "b25d2b47-798b-4b88-949e-8ca46f59c3eb",
  "data": [
    {
      "entity": "OTRO_NUMERO_IDENTIF",
      "text": "HC-2024-789123"
    },
    {
      "entity": "PROFESION",
      "text": "cirujano"
    },
    {
      "entity": "INSTITUCION",
      "text": "Ministerio de Sanidad"
    },
    {
      "entity": "INSTITUCION",
      "text": "Consejería de Salud de la Comunidad de Madrid"
    },
    {
      "entity": "IDENTIF_DISPOSITIVOS_NRSERIE",
      "text": "SN-98237641"
    },
    {
      "entity": "URL_WEB",
      "text": "https://www.clinicabarcelona.org"
    },
    {
      "entity": "FAMILIARES_SUJETO_ASISTENCIA",
      "text": "María Fernández López"
    }
  ]
}