{
  "id": "b7e0771f-4b14-4444-bea2-91af23880817",
  "data": [
    {
      "entity": "ID_TITULACION_PERSONAL_SANITARIO",
      "text": "Grado en Enfermería"
    },
    {
      "entity": "ID_TITULACION_PERSONAL_SANITARIO",
      "text": "Grado en Medicina"
    },
    {
      "entity": "OTRO_NUMERO_IDENTIF",
      "text": "HC-2024-789012"
    },
    {
      "entity": "NOMBRE_PERSONAL_SANITARIO",
      "text": "Dra. Elena Rodríguez Santos"
    },
    {
      "entity": "IDENTIF_DISPOSITIVOS_NRSERIE",
      "text": "SN-98246731"
    },
    {
      "entity": "NOMBRE_SUJETO_ASISTENCIA",
      "text": "Laura Méndez Iglesias"
    },
    {
      "entity": "ID_ASEGURAMIENTO",
      "text": "46 08 28 123 45"
    },
    {
      "entity": "PAIS",
      "text": "España"
    },
    {
      "entity": "NUMERO_BENEF_PLAN_SALUD",
      "text": "B-45872316"
    },
    {
      "entity": "INSTITUCION",
      "text": "Consejería de Sanidad de la Comunidad de Madrid"
    },
    {
      "entity": "INSTITUCION",
      "text": "Consejería de Salud de la Comunidad de Madrid"
    }
  ]
}