{
  "id": "b8cc0e85-2efa-4f48-9ded-e49d23029f1f",
  "data": [
    {
      "entity": "URL_WEB",
      "text": "https://www.clinicabarcelona.es"
    },
    {
      "entity": "DIREC_PROT_INTERNET",
      "text": "https://www.hospitalregional.es/pacientes/consulta-resultados"
    },
    {
      "entity": "SEXO_SUJETO_ASISTENCIA",
      "text": "femenino"
    },
    {
      "entity": "NOMBRE_SUJETO_ASISTENCIA",
      "text": "Laura Méndez Iglesias"
    },
    {
      "entity": "ID_SUJETO_ASISTENCIA",
      "text": "87654321B"
    },
    {
      "entity": "NUMERO_BENEF_PLAN_SALUD",
      "text": "B-45872316"
    },
    {
      "entity": "NUMERO_BENEF_PLAN_SALUD",
      "text": "B-458712369"
    },
    {
      "entity": "OTRO_NUMERO_IDENTIF",
      "text": "REF-48263915B"
    },
    {
      "entity": "OTRO_NUMERO_IDENTIF",
      "text": "HC-2024-789012"
    }
  ]
}