{
  "id": "bfd43d31-645e-472c-855b-faaccdcdd336",
  "data": [
    {
      "entity": "ID_TITULACION_PERSONAL_SANITARIO",
      "text": "Grado en Medicina"
    },
    {
      "entity": "OTRO_NUMERO_IDENTIF",
      "text": "REF-48263915B"
    },
    {
      "entity": "OTRO_NUMERO_IDENTIF",
      "text": "REF-874209"
    },
    {
      "entity": "NUMERO_TELEFONO",
      "text": "+34 612 34 56 78"
    },
    {
      "entity": "ID_SUJETO_ASISTENCIA",
      "text": "73482914B"
    },
    {
      "entity": "ID_SUJETO_ASISTENCIA",
      "text": "87654321B"
    },
    {
      "entity": "PAIS",
      "text": "España"
    },
    {
      "entity": "NUMERO_BENEF_PLAN_SALUD",
      "text": "B-87654321"
    },
    {
      "entity": "ID_CONTACTO_ASISTENCIAL",
      "text": "HC-2024-789012"
    }
  ]
}