{
  "id": "c4dee916-17a4-4b6a-a3db-27d8d6ae6d73",
  "data": [
    {
      "entity": "FECHAS",
      "text": "12 de julio de 2023"
    },
    {
      "entity": "PAIS",
      "text": "España"
    },
    {
      "entity": "ID_EMPLEO_PERSONAL_SANITARIO",
      "text": "E-987654"
    },
    {
      "entity": "TERRITORIO",
      "text": "Comunidad Valenciana"
    },
    {
      "entity": "ID_SUJETO_ASISTENCIA",
      "text": "87654321B"
    },
    {
      "entity": "NOMBRE_PERSONAL_SANITARIO",
      "text": "Dra. Elena Rodríguez Santos"
    }
  ]
}