{
  "id": "cbaf8a31-6b49-4c3d-8857-4b5b7b8e32e6",
  "data": [
    {
      "entity": "IDENTIF_DISPOSITIVOS_NRSERIE",
      "text": "SN-98765432"
    },
    {
      "entity": "CENTRO_SALUD",
      "text": "Centro de Salud Los Álamos"
    },
    {
      "entity": "PAIS",
      "text": "España"
    },
    {
      "entity": "INSTITUCION",
      "text": "Ministerio de Sanidad"
    },
    {
      "entity": "ID_SUJETO_ASISTENCIA",
      "text": "87654321B"
    },
    {
      "entity": "NUMERO_FAX",
      "text": "+34 91 876 54 32"
    },
    {
      "entity": "ID_ASEGURAMIENTO",
      "text": "B123456789012"
    },
    {
      "entity": "ID_ASEGURAMIENTO",
      "text": "B123456789"
    },
    {
      "entity": "NUMERO_TELEFONO",
      "text": "612-34-56-78"
    }
  ]
}