{
  "id": "cf23a9e3-fd22-47a5-8ef3-be0c0064c88a",
  "data": [
    {
      "entity": "OTROS_SUJETO_ASISTENCIA",
      "text": "fumador ocasional"
    },
    {
      "entity": "NOMBRE_PERSONAL_SANITARIO",
      "text": "Dra. Elena Rodríguez Santos"
    },
    {
      "entity": "OTRO_NUMERO_IDENTIF",
      "text": "REF-789456123"
    },
    {
      "entity": "OTRO_NUMERO_IDENTIF",
      "text": "REF-2024-789012"
    },
    {
      "entity": "NUMERO_TELEFONO",
      "text": "612-345-678"
    },
    {
      "entity": "HOSPITAL",
      "text": "Hospital Clínico San Carlos"
    },
    {
      "entity": "ID_CONTACTO_ASISTENCIAL",
      "text": "CONT-2024-789123"
    },
    {
      "entity": "ID_CONTACTO_ASISTENCIAL",
      "text": "HC-2024-789012"
    }
  ]
}