{
  "id": "d11bb357-e553-46e0-a2c1-b8d70ff20f52",
  "data": [
    {
      "entity": "HOSPITAL",
      "text": "Hospital Clínico San Carlos"
    },
    {
      "entity": "DIREC_PROT_INTERNET",
      "text": "https://historiaclinica.hgugm.es/paciente/12345678A"
    },
    {
      "entity": "NUMERO_BENEF_PLAN_SALUD",
      "text": "B123456789"
    },
    {
      "entity": "NUMERO_BENEF_PLAN_SALUD",
      "text": "B-458712369"
    },
    {
      "entity": "ID_CONTACTO_ASISTENCIAL",
      "text": "HC-2024-789123"
    },
    {
      "entity": "NOMBRE_PERSONAL_SANITARIO",
      "text": "Dra. Elena Martínez Ruiz"
    },
    {
      "entity": "NOMBRE_PERSONAL_SANITARIO",
      "text": "Dra. Elena Rodríguez Santos"
    }
  ]
}