{
  "id": "d2f34eda-732b-43a2-b422-8f1620cd3f2b",
  "data": [
    {
      "entity": "NOMBRE_SUJETO_ASISTENCIA",
      "text": "Laura Méndez Iglesias"
    },
    {
      "entity": "CORREO_ELECTRONICO",
      "text": "ana.martinez@clinic.es"
    },
    {
      "entity": "PROFESION",
      "text": "cirujano"
    },
    {
      "entity": "SEXO_SUJETO_ASISTENCIA",
      "text": "femenino"
    },
    {
      "entity": "CENTRO_SALUD",
      "text": "Centro de Salud Los Álamos"
    },
    {
      "entity": "DIREC_PROT_INTERNET",
      "text": "https://historiaclinica.hospitalregional.es/paciente/consulta"
    },
    {
      "entity": "DIREC_PROT_INTERNET",
      "text": "https://historiaclinica.hgugm.es/paciente/12345678A"
    },
    {
      "entity": "ID_CONTACTO_ASISTENCIAL",
      "text": "HC-2024-789012"
    }
  ]
}