{
  "id": "d6650d94-94b1-4f88-b3a4-7c0b02a79821",
  "data": [
    {
      "entity": "FAMILIARES_SUJETO_ASISTENCIA",
      "text": "María del Carmen López"
    },
    {
      "entity": "FAMILIARES_SUJETO_ASISTENCIA",
      "text": "María García López"
    },
    {
      "entity": "NOMBRE_SUJETO_ASISTENCIA",
      "text": "Laura Méndez Iglesias"
    },
    {
      "entity": "SEXO_SUJETO_ASISTENCIA",
      "text": "femenino"
    },
    {
      "entity": "NUMERO_BENEF_PLAN_SALUD",
      "text": "B-45872316"
    },
    {
      "entity": "IDENTIF_VEHICULOS_NRSERIE_PLACAS",
      "text": "1234 BCD"
    },
    {
      "entity": "IDENTIF_BIOMETRICOS",
      "text": "huella dactilar derecha índice"
    },
    {
      "entity": "ID_TITULACION_PERSONAL_SANITARIO",
      "text": "Grado en Enfermería"
    }
  ]
}