{
  "id": "dbb9ba83-b1b1-4d42-b87e-505f650d2a6d",
  "data": [
    {
      "entity": "HOSPITAL",
      "text": "Hospital Clínico San Carlos"
    },
    {
      "entity": "DIREC_PROT_INTERNET",
      "text": "https://historiaclinica.hgugm.es/paciente/AB12345CD"
    },
    {
      "entity": "DIREC_PROT_INTERNET",
      "text": "https://historiaclinica.hgugm.es/paciente/12345678A"
    },
    {
      "entity": "NUMERO_BENEF_PLAN_SALUD",
      "text": "B-45872316"
    },
    {
      "entity": "ID_ASEGURAMIENTO",
      "text": "46 08 28 123 45"
    },
    {
      "entity": "ID_ASEGURAMIENTO",
      "text": "B123456789"
    },
    {
      "entity": "FECHAS",
      "text": "12 de julio de 2023"
    }
  ]
}