{
  "id": "e3df5aaa-d433-4e48-b49a-3ab64544ed85",
  "data": [
    {
      "entity": "ID_CONTACTO_ASISTENCIAL",
      "text": "HC-2024-789123"
    },
    {
      "entity": "ID_CONTACTO_ASISTENCIAL",
      "text": "HC-2023-847215"
    },
    {
      "entity": "IDENTIF_VEHICULOS_NRSERIE_PLACAS",
      "text": "1234 BCD"
    },
    {
      "entity": "FECHAS",
      "text": "12 de julio de 2023"
    },
    {
      "entity": "IDENTIF_BIOMETRICOS",
      "text": "huella dactilar derecha índice"
    },
    {
      "entity": "NOMBRE_SUJETO_ASISTENCIA",
      "text": "Laura Méndez Iglesias"
    },
    {
      "entity": "FAMILIARES_SUJETO_ASISTENCIA",
      "text": "María González Martínez"
    },
    {
      "entity": "CORREO_ELECTRONICO",
      "text": "carlos.martinez@clinic.es"
    },
    {
      "entity": "NUMERO_TELEFONO",
      "text": "612-345-678"
    },
    {
      "entity": "NOMBRE_PERSONAL_SANITARIO",
      "text": "Dra. Elena Rodríguez Santos"
    }
  ]
}