{
  "id": "e9b5114c-97bb-41b8-bb73-7f2199933949",
  "data": [
    {
      "entity": "CORREO_ELECTRONICO",
      "text": "carlos.martinez@clinic.es"
    },
    {
      "entity": "OTRO_NUMERO_IDENTIF",
      "text": "HC-2024-789456"
    },
    {
      "entity": "OTROS_SUJETO_ASISTENCIA",
      "text": "Grupo de apoyo de diabetes tipo 2"
    },
    {
      "entity": "OTROS_SUJETO_ASISTENCIA",
      "text": "Grupo de apoyo para pacientes oncológicos"
    },
    {
      "entity": "DIREC_PROT_INTERNET",
      "text": "https://historiaclinica.hgugm.es/paciente/12345678A"
    },
    {
      "entity": "ID_EMPLEO_PERSONAL_SANITARIO",
      "text": "E-789456"
    },
    {
      "entity": "TERRITORIO",
      "text": "Comunidad Valenciana"
    },
    {
      "entity": "URL_WEB",
      "text": "https://www.clinicabarcelona.org"
    },
    {
      "entity": "URL_WEB",
      "text": "https://www.clinicabarcelona.es"
    },
    {
      "entity": "NUMERO_TELEFONO",
      "text": "+34 612 34 56 78"
    },
    {
      "entity": "HOSPITAL",
      "text": "Hospital Clínico San Carlos"
    }
  ]
}