{
  "id": "f4c7400d-eba0-4133-99af-ea3da1878a7f",
  "data": [
    {
      "entity": "INSTITUCION",
      "text": "Ministerio de Sanidad"
    },
    {
      "entity": "NOMBRE_SUJETO_ASISTENCIA",
      "text": "Laura Méndez Iglesias"
    },
    {
      "entity": "TERRITORIO",
      "text": "Comunidad Valenciana"
    },
    {
      "entity": "FAMILIARES_SUJETO_ASISTENCIA",
      "text": "María del Carmen Fernández"
    },
    {
      "entity": "FAMILIARES_SUJETO_ASISTENCIA",
      "text": "María García López"
    },
    {
      "entity": "NUMERO_TELEFONO",
      "text": "+34 612 34 56 78"
    },
    {
      "entity": "NUMERO_TELEFONO",
      "text": "612-34-56-78"
    },
    {
      "entity": "ID_EMPLEO_PERSONAL_SANITARIO",
      "text": "E-987654"
    },
    {
      "entity": "ID_SUJETO_ASISTENCIA",
      "text": "87654321B"
    },
    {
      "entity": "CALLE",
      "text": "Avenida de la Constitución 12"
    },
    {
      "entity": "NUMERO_FAX",
      "text": "+34 91 876 54 32"
    },
    {
      "entity": "ID_CONTACTO_ASISTENCIAL",
      "text": "HC-2024-789012"
    }
  ]
}