{
  "id": "fb127329-bf1d-472f-842d-b16071888018",
  "data": [
    {
      "entity": "IDENTIF_VEHICULOS_NRSERIE_PLACAS",
      "text": "1234 BCD"
    },
    {
      "entity": "HOSPITAL",
      "text": "Hospital Clínico San Carlos"
    },
    {
      "entity": "IDENTIF_DISPOSITIVOS_NRSERIE",
      "text": "SN-98237641"
    },
    {
      "entity": "URL_WEB",
      "text": "https://www.clinicabarcelona.org"
    },
    {
      "entity": "OTRO_NUMERO_IDENTIF",
      "text": "REF-48263915B"
    },
    {
      "entity": "OTRO_NUMERO_IDENTIF",
      "text": "REF-789456123"
    },
    {
      "entity": "OTRO_NUMERO_IDENTIF",
      "text": "REF-7348291B"
    },
    {
      "entity": "EDAD_SUJETO_ASISTENCIA",
      "text": "67 años"
    },
    {
      "entity": "ID_CONTACTO_ASISTENCIAL",
      "text": "HC-2024-789123"
    },
    {
      "entity": "ID_CONTACTO_ASISTENCIAL",
      "text": "CON-2024-789123"
    },
    {
      "entity": "ID_CONTACTO_ASISTENCIAL",
      "text": "ID-CONT-784512"
    },
    {
      "entity": "FAMILIARES_SUJETO_ASISTENCIA",
      "text": "María del Carmen Rodríguez, esposa"
    },
    {
      "entity": "TERRITORIO",
      "text": "Comunidad Valenciana"
    },
    {
      "entity": "IDENTIF_BIOMETRICOS",
      "text": "huella dactilar derecha índice, patrón de lazo"
    },
    {
      "entity": "SEXO_SUJETO_ASISTENCIA",
      "text": "femenino"
    },
    {
      "entity": "OTROS_SUJETO_ASISTENCIA",
      "text": "Grupo de apoyo de ansiedad"
    }
  ]
}