{
  "id": "fcd43b6b-c5d5-4ed4-82be-a49f8728f31b",
  "data": [
    {
      "entity": "INSTITUCION",
      "text": "Ministerio de Sanidad"
    },
    {
      "entity": "EDAD_SUJETO_ASISTENCIA",
      "text": "78 años"
    },
    {
      "entity": "CALLE",
      "text": "Avenida de la Constitución 12"
    },
    {
      "entity": "CORREO_ELECTRONICO",
      "text": "carlos.martinez@clinic.es"
    },
    {
      "entity": "IDENTIF_BIOMETRICOS",
      "text": "huella dactilar derecha índice"
    },
    {
      "entity": "PROFESION",
      "text": "cirujano"
    },
    {
      "entity": "TERRITORIO",
      "text": "Comunidad Valenciana"
    },
    {
      "entity": "ID_TITULACION_PERSONAL_SANITARIO",
      "text": "Grado en Medicina"
    }
  ]
}