{
  "id": "ff3958af-9bbc-49c5-930b-eab6be6b4605",
  "data": [
    {
      "entity": "IDENTIF_DISPOSITIVOS_NRSERIE",
      "text": "SN-98237641"
    },
    {
      "entity": "OTRO_NUMERO_IDENTIF",
      "text": "HC-2024-789012"
    },
    {
      "entity": "OTRO_NUMERO_IDENTIF",
      "text": "B-58342901"
    },
    {
      "entity": "OTRO_NUMERO_IDENTIF",
      "text": "REF-789456123"
    },
    {
      "entity": "PAIS",
      "text": "España"
    },
    {
      "entity": "CORREO_ELECTRONICO",
      "text": "carlos.martinez@clinic.es"
    },
    {
      "entity": "CORREO_ELECTRONICO",
      "text": "lucia.martinez@clinic.es"
    },
    {
      "entity": "CORREO_ELECTRONICO",
      "text": "ana.martinez@clinic.es"
    },
    {
      "entity": "HOSPITAL",
      "text": "Hospital Clínico San Carlos"
    },
    {
      "entity": "ID_CONTACTO_ASISTENCIAL",
      "text": "HC-2024-789123"
    }
  ]
}